chateau/__init__.py
chateau/config.py
chateau/auth/__init__.py
chateau/auth/forms.py
chateau/auth/routes.py
chateau/database/__init__.py
chateau/database/auth.py
chateau/database/connection.py
chateau/game/__init__.py
chateau/game/routes.py
chateau/play/__init__.py
chateau/play/routes.py
chateau/redis/__init__.py
chateau/session/__init__.py
chateau/session/session.py
chateau/settings/__init__.py
chateau/settings/forms.py
chateau/settings/routes.py
chateau/stats/__init__.py
chateau/stats/forms.py
chateau/stats/routes.py
chateau/websocket/__init__.py
chateau-1.0.0.dist-info/LICENSE
chateau-1.0.0.dist-info/METADATA
chateau-1.0.0.dist-info/WHEEL
chateau-1.0.0.dist-info/top_level.txt
chateau-1.0.0.dist-info/RECORD
