Metadata-Version: 2.1
Name: chateau
Version: 1.0.0
Summary: Central services.
Home-page: https://github.com/softwerks/chateau
Author: Softwerks
Author-email: info@softwerks.com
License: UNKNOWN
Platform: UNKNOWN
Classifier: Programming Language :: Python :: 3
Classifier: License :: OSI Approved :: Apache Software License
Classifier: Operating System :: OS Independent
Requires-Python: >=3.7
License-File: LICENSE
Requires-Dist: email-validator
Requires-Dist: flask
Requires-Dist: Flask-WTF
Requires-Dist: hiredis
Requires-Dist: psycopg2
Requires-Dist: python-dateutil
Requires-Dist: redis
